{"status":"done","chunks":{"app":["js/chunk-vendors.js","js/app.js"]},"publicPath":"http://localhost:8080/","assets":{"img/logo.svg":{"name":"img/logo.svg","path":"D:\\Others\\backend\\django_vue_mpa\\static\\vue\\img\\logo.svg","publicPath":"http://localhost:8080/img/logo.svg"},"js/app.js":{"name":"js/app.js","path":"D:\\Others\\backend\\django_vue_mpa\\static\\vue\\js\\app.js","publicPath":"http://localhost:8080/js/app.js"},"js/chunk-vendors.js":{"name":"js/chunk-vendors.js","path":"D:\\Others\\backend\\django_vue_mpa\\static\\vue\\js\\chunk-vendors.js","publicPath":"http://localhost:8080/js/chunk-vendors.js"},"index.html":{"name":"index.html","path":"D:\\Others\\backend\\django_vue_mpa\\static\\vue\\index.html","publicPath":"http://localhost:8080/index.html"},"favicon.ico":{"name":"favicon.ico","path":"D:\\Others\\backend\\django_vue_mpa\\static\\vue\\favicon.ico","publicPath":"http://localhost:8080/favicon.ico"}}}